{
  "storyid": "hon-the-cua-toi-that-xau-tinh!-0",
  "storyname": "hôn thê của tôi thật xấu tính!",
  "storyothername": "Boku no Ikezuna Konyakusha",
  "storyimage": "https://admin.nettruyentranh.com/Pictures/Truyen/Large/hon-the-cua-toi-that-xau-tinh!.jpg",
  "storydes": "Miyuki là một tiểu thư sinh ra ở Kyoto. Mối quan hệ của tôi với cô ấy không ổn lắm. Bởi vì câu nói... “Cậu giỏi nịnh người khác thật nhỉ?”. Những lời ấy cậu ấy ghét mình  hay có ẩn ý?. Đây là một câu chuyện tình đầy rẫy sự hiểm lầm.",
  "storygenres": "Comedy, Romance, School Life",
  "urllinkcraw": "https://nettruyentranh.com/hon-the-cua-toi-that-xau-tinh!-0.html",
  "storytauthor": "",
  "views": "64"
}
