{
  "storyid": "toan-dan-chuyen-chuc--duy-ta-vo-chuc-tan-nhan-1-0",
  "storyname": "Toàn Dân Chuyển Chức : Duy Ta Vô Chức Tán Nhân",
  "storyothername": "",
  "storyimage": "https://admin.nettruyentranh.com/Pictures/Truyen/Large/toan-dan-chuyen-chuc--duy-ta-vo-chuc-tan-nhan_1.jpg",
  "storydes": "một năm kia, toàn cầu dị biến, trò chơi hàng lâm hiện thực, ma tai bắt đầu tàn sát bừa bãi.vì chống lại đây hết thảy, mỗi một cái người đều muốn quy hoạch chức nghiệp tuyển hạng, điên cuồng thăng cấp, tranh thủ mạnh mẽ.có người lựa chọn cao quý pháp gia, nhị chuyển quyết định nguyên tố pháp sư.có người tuyển chọn triệu hoán sư, dưới cờ triệu hoán vật liên tiếp xuất hiện, quần ẩu chết địch nhân.có thể khiến người mở rộng tầm mắt là, bị đặt vào kỳ vọng cao thi đại học sinh vân thần cũng là tuyển trạch không chuyển chức, làm một cái không chức nghiệp tán nhân!",
  "storygenres": "Action, Chuyển Sinh, Manhua, Manhwa, Mystery, Xuyên Không",
  "urllinkcraw": "https://nettruyentranh.com/toan-dan-chuyen-chuc--duy-ta-vo-chuc-tan-nhan-1-0.html",
  "storytauthor": "Đang cập nhật",
  "views": "4643"
}
